{
  "pageNumber": 235,
  "qiraatId": "ibn_amir_dhakwan",
  "ayahs": [
    {
      "surahNumber": 11,
      "ayahNumber": 109,
      "positions": [
        {
          "x": 0.15,
          "y": 1.0699999999999998,
          "width": 0.7,
          "height": 0.08,
          "lineNumber": 0
        }
      ]
    },
    {
      "surahNumber": 11,
      "ayahNumber": 110,
      "positions": [
        {
          "x": 0.15,
          "y": 0.35,
          "width": 0.7,
          "height": 0.08,
          "lineNumber": 0
        }
      ]
    },
    {
      "surahNumber": 11,
      "ayahNumber": 111,
      "positions": [
        {
          "x": 0.15,
          "y": 0.43,
          "width": 0.7,
          "height": 0.08,
          "lineNumber": 0
        }
      ]
    },
    {
      "surahNumber": 11,
      "ayahNumber": 112,
      "positions": [
        {
          "x": 0.15,
          "y": 0.51,
          "width": 0.7,
          "height": 0.08,
          "lineNumber": 0
        }
      ]
    },
    {
      "surahNumber": 11,
      "ayahNumber": 113,
      "positions": [
        {
          "x": 0.15,
          "y": 0.59,
          "width": 0.7,
          "height": 0.08,
          "lineNumber": 0
        }
      ]
    },
    {
      "surahNumber": 11,
      "ayahNumber": 114,
      "positions": [
        {
          "x": 0.15,
          "y": 0.6699999999999999,
          "width": 0.7,
          "height": 0.08,
          "lineNumber": 0
        }
      ]
    },
    {
      "surahNumber": 11,
      "ayahNumber": 115,
      "positions": [
        {
          "x": 0.15,
          "y": 0.75,
          "width": 0.7,
          "height": 0.08,
          "lineNumber": 0
        }
      ]
    },
    {
      "surahNumber": 11,
      "ayahNumber": 116,
      "positions": [
        {
          "x": 0.15,
          "y": 0.83,
          "width": 0.7,
          "height": 0.08,
          "lineNumber": 0
        }
      ]
    },
    {
      "surahNumber": 11,
      "ayahNumber": 117,
      "positions": [
        {
          "x": 0.15,
          "y": 0.91,
          "width": 0.7,
          "height": 0.08,
          "lineNumber": 0
        }
      ]
    }
  ]
}